odoo/addons/account_bill_line_distribution/README.rst
odoo/addons/account_bill_line_distribution/__init__.py
odoo/addons/account_bill_line_distribution/__manifest__.py
odoo/addons/account_bill_line_distribution/i18n/account_bill_line_distribution.pot
odoo/addons/account_bill_line_distribution/models/__init__.py
odoo/addons/account_bill_line_distribution/models/account_bill_line_distribution.py
odoo/addons/account_bill_line_distribution/models/account_invoice.py
odoo/addons/account_bill_line_distribution/models/account_invoice_line.py
odoo/addons/account_bill_line_distribution/readme/CONFIGURE.rst
odoo/addons/account_bill_line_distribution/readme/CONTRIBUTORS.rst
odoo/addons/account_bill_line_distribution/readme/DESCRIPTION.rst
odoo/addons/account_bill_line_distribution/readme/USAGE.rst
odoo/addons/account_bill_line_distribution/security/ir.model.access.csv
odoo/addons/account_bill_line_distribution/security/ir_rule.xml
odoo/addons/account_bill_line_distribution/static/description/icon.png
odoo/addons/account_bill_line_distribution/static/description/index.html
odoo/addons/account_bill_line_distribution/views/account_invoice.xml
odoo12_addon_account_bill_line_distribution-12.0.1.0.0.99.dev23.dist-info/METADATA
odoo12_addon_account_bill_line_distribution-12.0.1.0.0.99.dev23.dist-info/WHEEL
odoo12_addon_account_bill_line_distribution-12.0.1.0.0.99.dev23.dist-info/top_level.txt
odoo12_addon_account_bill_line_distribution-12.0.1.0.0.99.dev23.dist-info/RECORD
